cdlib/__init__.py
cdlib/prompt_utils.py
cdlib/utils.py
cdlib/algorithms/__init__.py
cdlib/algorithms/attribute_clustering.py
cdlib/algorithms/bipartite_clustering.py
cdlib/algorithms/crisp_partition.py
cdlib/algorithms/edge_clustering.py
cdlib/algorithms/overlapping_partition.py
cdlib/algorithms/temporal_partition.py
cdlib/algorithms/internal/AGDL.py
cdlib/algorithms/internal/BIGCLAM.py
cdlib/algorithms/internal/COACH.py
cdlib/algorithms/internal/CONGA.py
cdlib/algorithms/internal/CONGO.py
cdlib/algorithms/internal/DCS.py
cdlib/algorithms/internal/DER.py
cdlib/algorithms/internal/DPCLUS.py
cdlib/algorithms/internal/EBGC.py
cdlib/algorithms/internal/EnDNTM.py
cdlib/algorithms/internal/FuzzyCom.py
cdlib/algorithms/internal/GDMP2_nx.py
cdlib/algorithms/internal/HLC.py
cdlib/algorithms/internal/ILouvain.py
cdlib/algorithms/internal/IPCA.py
cdlib/algorithms/internal/Kcut.py
cdlib/algorithms/internal/LAIS2_nx.py
cdlib/algorithms/internal/LEMON.py
cdlib/algorithms/internal/LPAM.py
cdlib/algorithms/internal/LPANNI.py
cdlib/algorithms/internal/LSWL.py
cdlib/algorithms/internal/MCODE.py
cdlib/algorithms/internal/Markov.py
cdlib/algorithms/internal/NodePerception.py
cdlib/algorithms/internal/OSSE.py
cdlib/algorithms/internal/PercoMCV.py
cdlib/algorithms/internal/RSC.py
cdlib/algorithms/internal/SLPA_nx.py
cdlib/algorithms/internal/SiblinarityAntichain.py
cdlib/algorithms/internal/UMSTMO.py
cdlib/algorithms/internal/__init__.py
cdlib/algorithms/internal/belief_prop.py
cdlib/algorithms/internal/core_exp.py
cdlib/algorithms/internal/em.py
cdlib/algorithms/internal/ga.py
cdlib/algorithms/internal/graph_entropy.py
cdlib/algorithms/internal/headtail.py
cdlib/algorithms/internal/lfm.py
cdlib/algorithms/internal/markov_clustering.py
cdlib/algorithms/internal/modularity_m.py
cdlib/algorithms/internal/modularity_r.py
cdlib/algorithms/internal/multicom.py
cdlib/algorithms/internal/paris.py
cdlib/algorithms/internal/principled.py
cdlib/algorithms/internal/pycondor.py
cdlib-0.4.0.dist-info/LICENSE
cdlib-0.4.0.dist-info/METADATA
cdlib-0.4.0.dist-info/WHEEL
cdlib-0.4.0.dist-info/top_level.txt
cdlib-0.4.0.dist-info/RECORD
