Metadata-Version: 2.1
Name: cdlib
Version: 0.4.0
Summary: Community Discovery Library
Home-page: https://github.com/GiulioRossetti/cdlib
Author: Giulio Rossetti
Author-email: giulio.rossetti@gmail.com
License: BSD-Clause-2
Keywords: community-discovery node-clustering edge-clustering complex-networks
Classifier: Development Status :: 4 - Beta
Classifier: Intended Audience :: Developers
Classifier: Topic :: Software Development :: Build Tools
Classifier: License :: OSI Approved :: BSD License
Classifier: Operating System :: POSIX :: Other
Classifier: Operating System :: MacOS
Classifier: Programming Language :: Python
Classifier: Programming Language :: Python :: 3
License-File: LICENSE
Requires-Dist: numpy
Requires-Dist: scikit-learn
Requires-Dist: tqdm
Requires-Dist: networkx (>=3.0)
Requires-Dist: demon
Requires-Dist: python-louvain (>=0.16)
Requires-Dist: scipy (>=1.10)
Requires-Dist: pulp
Requires-Dist: seaborn
Requires-Dist: pandas
Requires-Dist: eva-lcd
Requires-Dist: bimlpa
Requires-Dist: python-igraph (>=0.10)
Requires-Dist: angelcommunity
Requires-Dist: pooch
Requires-Dist: dynetx
Requires-Dist: thresholdclustering
Requires-Dist: python-Levenshtein
Requires-Dist: plotly
Provides-Extra: c
Requires-Dist: infomap (>=1.3.0) ; extra == 'c'
Requires-Dist: wurlitzer (>=1.0.2) ; extra == 'c'
Requires-Dist: GraphRicciCurvature ; extra == 'c'
Requires-Dist: networkit ; extra == 'c'
Requires-Dist: pycombo ; extra == 'c'
Requires-Dist: leidenalg ; extra == 'c'
Provides-Extra: all
Requires-Dist: infomap (>=1.3.0) ; extra == 'all'
Requires-Dist: wurlitzer (>=1.0.2) ; extra == 'all'
Requires-Dist: GraphRicciCurvature ; extra == 'all'
Requires-Dist: networkit ; extra == 'all'
Requires-Dist: pycombo ; extra == 'all'
Requires-Dist: leidenalg ; extra == 'all'
Requires-Dist: bayanpy ; extra == 'all'
Requires-Dist: pyclustering ; extra == 'all'
Requires-Dist: clusim ; extra == 'all'
Provides-Extra: pypi
Requires-Dist: bayanpy ; extra == 'pypi'
Requires-Dist: pyclustering ; extra == 'pypi'
Requires-Dist: clusim ; extra == 'pypi'
